pythod/__init__.py
pythod/config.json
pythod/configuration.py
pythod/configuration_deserializer.py
pythod/content.py
pythod/main.py
pythod/organizer.py
pythod-0.0.6.dist-info/LICENCE
pythod-0.0.6.dist-info/METADATA
pythod-0.0.6.dist-info/WHEEL
pythod-0.0.6.dist-info/entry_points.txt
pythod-0.0.6.dist-info/top_level.txt
pythod-0.0.6.dist-info/RECORD
