Metadata-Version: 2.1
Name: pythod
Version: 0.0.6
Summary: Pythod is a lightweigh Python directory organizing CLI tool.
Home-page: https://github.com/not-so-cool-anymore/pythod
Author: Ivan Zlatanov
Author-email: i_zlatanov@protonmail.com
License: UNKNOWN
Platform: UNKNOWN
Classifier: Programming Language :: Python :: 3
Classifier: License :: OSI Approved :: GNU General Public License v3 or later (GPLv3+)
Classifier: Operating System :: OS Independent
Requires-Python: >=3.5
